{
  "$type": "DT.MdmMetadata.Types.HandlerFunction1C, DT_Core",
  "Synchronously": false,
  "Integration": "ToPlatform",
  "Type": "Function1C",
  "Code": "[Handler] ПроверитьЗначениеСвойстваОбъектаУТ [Code].ext",
  "WaitResponse": false,
  "SubscriptionObject": "",
  "SystemDataTypeId": null,
  "Parameters": [
    {
      "$type": "DT.MdmMetadata.BusinessProcesses.Fields.SimpleField, DT_Core",
      "Type": "String",
      "DecimalOptions": null,
      "StringOptions": null,
      "DateTimeOptions": null,
      "Name": "СсылкаНаОбъект",
      "Id": "c0cde545-eac8-4f24-9a71-6ea13cf86df1",
      "IsArray": false,
      "IsRequired": false,
      "IsNullable": false,
      "Description": "",
      "Properties": {
        "$type": "System.Collections.Generic.Dictionary`2[[System.String, System.Private.CoreLib],[System.String, System.Private.CoreLib]], System.Private.CoreLib"
      },
      "AttributeId": "00000000-0000-0000-0000-000000000000"
    },
    {
      "$type": "DT.MdmMetadata.BusinessProcesses.Fields.SimpleField, DT_Core",
      "Type": "String",
      "DecimalOptions": null,
      "StringOptions": null,
      "DateTimeOptions": null,
      "Name": "ИмяСвойства",
      "Id": "55e03979-8395-4a0f-b687-ec9be05a9255",
      "IsArray": false,
      "IsRequired": false,
      "IsNullable": false,
      "Description": "",
      "Properties": {
        "$type": "System.Collections.Generic.Dictionary`2[[System.String, System.Private.CoreLib],[System.String, System.Private.CoreLib]], System.Private.CoreLib"
      },
      "AttributeId": "00000000-0000-0000-0000-000000000000"
    },
    {
      "$type": "DT.MdmMetadata.BusinessProcesses.Fields.SimpleField, DT_Core",
      "Type": "String",
      "DecimalOptions": null,
      "StringOptions": null,
      "DateTimeOptions": null,
      "Name": "ЗначениеДляПроверки",
      "Id": "fc51075f-79e4-443c-a71a-7a008b129fb4",
      "IsArray": false,
      "IsRequired": false,
      "IsNullable": false,
      "Description": "",
      "Properties": {
        "$type": "System.Collections.Generic.Dictionary`2[[System.String, System.Private.CoreLib],[System.String, System.Private.CoreLib]], System.Private.CoreLib"
      },
      "AttributeId": "00000000-0000-0000-0000-000000000000"
    }
  ],
  "Values": [],
  "DataFromPlatform": null,
  "DataToPlatform": null,
  "FolderId": "e2cb73fa-0b54-4c54-893a-4411061108b0",
  "EntityId": "ead3d58d-3f74-4999-b362-f45fcdb96fc9",
  "ClusterId": "c10ff86e-715b-4384-8a0c-f3cd82e3d74e",
  "Name": "ПроверитьЗначениеСвойстваОбъектаУТ",
  "Description": "Проверить значение свойства объекта УТ",
  "Comment": "Проверяет передаваемое значение свойства по РС \"ЗначениеСвойствОбъекта\"",
  "Version": 6,
  "TagsCollection": []
}